.travis.yml
CHANGES.rst
README.rst
conftest.py
pyramid_snippets.py
setup.cfg
setup.py
test_snippets.py
pyramid_snippets.egg-info/PKG-INFO
pyramid_snippets.egg-info/SOURCES.txt
pyramid_snippets.egg-info/dependency_links.txt
pyramid_snippets.egg-info/requires.txt
pyramid_snippets.egg-info/top_level.txt